imagewarp/__init__.py
imagewarp/hello_world.py
imagewarp-0.1.6.dist-info/licenses/LICENSE
imagewarp-0.1.6.dist-info/METADATA
imagewarp-0.1.6.dist-info/WHEEL
imagewarp-0.1.6.dist-info/top_level.txt
imagewarp-0.1.6.dist-info/RECORD
