Metadata-Version: 2.4
Name: imagewarp
Version: 0.1.6
Summary: Homography tools for 2D images and 3D volumes
Author-email: Andrew Polonsky <apolon@sandia.gov>
License: MIT License
Classifier: Programming Language :: Python :: 3
Classifier: License :: OSI Approved :: MIT License
Classifier: Operating System :: OS Independent
Requires-Python: >=3.11
License-File: LICENSE
Requires-Dist: numpy
Requires-Dist: pillow
Provides-Extra: dev
Requires-Dist: pytest; extra == "dev"
Requires-Dist: pytest-cov; extra == "dev"
Dynamic: license-file
